opentelemetry/instrumentation/fastapi/__init__.py
opentelemetry/instrumentation/fastapi/package.py
opentelemetry/instrumentation/fastapi/version.py
opentelemetry_instrumentation_fastapi-0.39b0.dist-info/METADATA
opentelemetry_instrumentation_fastapi-0.39b0.dist-info/WHEEL
opentelemetry_instrumentation_fastapi-0.39b0.dist-info/entry_points.txt
opentelemetry_instrumentation_fastapi-0.39b0.dist-info/licenses/LICENSE
opentelemetry_instrumentation_fastapi-0.39b0.dist-info/RECORD
