Metadata-Version: 2.1
Name: opentelemetry-instrumentation-fastapi
Version: 0.39b0
Summary: OpenTelemetry FastAPI Instrumentation
Project-URL: Homepage, https://github.com/open-telemetry/opentelemetry-python-contrib/tree/main/instrumentation/opentelemetry-instrumentation-fastapi
Author-email: OpenTelemetry Authors <cncf-opentelemetry-contributors@lists.cncf.io>
License-Expression: Apache-2.0
License-File: LICENSE
Classifier: Development Status :: 4 - Beta
Classifier: Intended Audience :: Developers
Classifier: License :: OSI Approved :: Apache Software License
Classifier: Programming Language :: Python
Classifier: Programming Language :: Python :: 3
Classifier: Programming Language :: Python :: 3.7
Classifier: Programming Language :: Python :: 3.8
Classifier: Programming Language :: Python :: 3.9
Classifier: Programming Language :: Python :: 3.10
Classifier: Programming Language :: Python :: 3.11
Requires-Python: >=3.7
Requires-Dist: opentelemetry-api~=1.12
Requires-Dist: opentelemetry-instrumentation-asgi==0.39b0
Requires-Dist: opentelemetry-instrumentation==0.39b0
Requires-Dist: opentelemetry-semantic-conventions==0.39b0
Requires-Dist: opentelemetry-util-http==0.39b0
Provides-Extra: instruments
Requires-Dist: fastapi~=0.58; extra == 'instruments'
Provides-Extra: test
Requires-Dist: httpx~=0.22; extra == 'test'
Requires-Dist: opentelemetry-instrumentation-fastapi[instruments]; extra == 'test'
Requires-Dist: opentelemetry-test-utils==0.39b0; extra == 'test'
Requires-Dist: requests~=2.23; extra == 'test'
